LICENSE
MANIFEST.in
README
requirements.txt
setup.py
./__init__.py
./alarm.py
./alarm_test.py
./credit.py
./credit_test.py
./filtered.py
./filtered_test.py
./lander.py
./misc.py
./misc_test.py
./pid.py
./pid_test.py
./trading_test.py
./version.py
./trading/__init__.py
./trading/actors.py
./trading/exchgs.py
ownercredit.egg-info/PKG-INFO
ownercredit.egg-info/SOURCES.txt
ownercredit.egg-info/dependency_links.txt
ownercredit.egg-info/top_level.txt